asyncgpiozero.py
asyncgpiozero-0.0.1a1.dist-info/WHEEL
asyncgpiozero-0.0.1a1.dist-info/METADATA
asyncgpiozero-0.0.1a1.dist-info/RECORD
