Metadata-Version: 2.1
Name: asyncgpiozero
Version: 0.0.1a1
Summary: asyncgpiozero
Home-page: https://github.com/ollipal
License: UNKNOWN
Author: ollipal
Classifier: License :: OSI Approved :: MIT License
